baul_app/__init__.py
baul_app/setup_v4.py
baul_app/baul/0DAY (ADM)/0day 3.0.0.ps1.FSEC
baul_app/baul/0DAY (ADM)/exploit.py.FSEC
baul_app/baul/Bat/hoaxell win pawn.txt.FSEC
baul_app/baul/Bat/serv hoaxell.txt.FSEC
baul_app/baul/Bypass (ADM)/Bypass Amsi win 10.txt.FSEC
baul_app/baul/Bypass (ADM)/Bypass Amsi win 11 y 10.py.FSEC
baul_app/baul/C y c++/keyloagger/hook.cpp.FSEC
baul_app/baul/C y c++/keyloagger/servidor.py.FSEC
baul_app/baul/Criptografia + Estega (ADM)/test.txt
baul_app/baul/Elf/test.txt
baul_app/baul/Exe Veridicos/calc.exe.FSEC
baul_app/baul/JS/tcp.js.FSEC
baul_app/baul/Laboratorio (ADM)/test.txt
baul_app/baul/N-DAY/test.txt
baul_app/baul/PROYECTO TSI (ADM)/Servidor v1.0.0.py.FSEC
baul_app/baul/PROYECTO TSI (ADM)/ServidorV2.py.FSEC
baul_app/baul/PROYECTO TSI (ADM)/ServidorV3.py.FSEC
baul_app/baul/PROYECTO TSI (ADM)/ServidorV4.py.FSEC
baul_app/baul/PROYECTO TSI (ADM)/cliente 1.0.0.py.FSEC
baul_app/baul/PROYECTO TSI (ADM)/clienteBeta.py.FSEC
baul_app/baul/PROYECTO TSI (ADM)/setup.py.FSEC
baul_app/baul/PROYECTO TSI (ADM)/test.py.FSEC
baul_app/baul/PROYECTO TSI (ADM)/templates/index.html.FSEC
baul_app/baul/Pentesting/test.txt
baul_app/baul/Powershell/backdoor TCP/tcp ofus Asembly.txt.FSEC
baul_app/baul/Powershell/backdoor TCP/tcp ofus TOKEN.txt.FSEC
baul_app/baul/Powershell/backdoor TCP/tcp sin ofuscar.txt.FSEC
baul_app/baul/Python/botwsp1.py.FSEC
baul_app/baul/Python/inyeccion comandos ram.py.FSEC
baul_app/baul/Python/kf.py.FSEC
baul_app/baul/Python/Sysops (ADM)/main.py.FSEC
baul_app/baul/Python/chatPRIV (ADM)/-i chat5-Prv-57214.portmap.io -p 57214.txt.FSEC
baul_app/baul/Python/chatPRIV (ADM)/authenticator.py.FSEC
baul_app/baul/Python/chatPRIV (ADM)/chat5-Prv.chat5.ovpn.FSEC
baul_app/baul/Python/chatPRIV (ADM)/chatPRIV.rar.FSEC
baul_app/baul/Python/chatPRIV (ADM)/cliente v6.0.1 - copia.py.FSEC
baul_app/baul/Python/chatPRIV (ADM)/cliente v6.0.1.py.FSEC
baul_app/baul/Python/chatPRIV (ADM)/requerimientos.txt.FSEC
kvx_0xbaul-1.1.0.dist-info/METADATA
kvx_0xbaul-1.1.0.dist-info/WHEEL
kvx_0xbaul-1.1.0.dist-info/entry_points.txt
kvx_0xbaul-1.1.0.dist-info/top_level.txt
kvx_0xbaul-1.1.0.dist-info/RECORD
