Metadata-Version: 2.4
Name: kvx-0xbaul
Version: 1.1.0
Summary: 0xBAUL - Interfaz de laboratorio
Author-email: Kovax00 <adx@ejemplo.com>
License: MIT
Requires-Python: >=3.8
Requires-Dist: customtkinter>=5.0.0
Requires-Dist: pycryptodome>=3.10
